opm/__init__.py
opm/bandpass.py
opm/covariance.py
opm/opm.py
opm/plot.py
opm/response.py
opm/stimuli.py
opm/gp/__init__.py
opm/gp/cholesky.py
opm/gp/gp.py
opm/gp/helpers.py
opm/gp/kernels.py
opm/gp/lowrank.py
opm/gp/match_radial_component.py
opm/gp/noise.py
opm/gp/prior.py
opm/gp/prior/__init__.py
opm/gp/prior/_prior.py
opm/gp/prior/cholesky.py
opm/gp/prior/kernels.py
opm/gp/prior/match_radial_component.py
gp_maps_python-0.0.3.dist-info/LICENSE
gp_maps_python-0.0.3.dist-info/METADATA
gp_maps_python-0.0.3.dist-info/WHEEL
gp_maps_python-0.0.3.dist-info/top_level.txt
gp_maps_python-0.0.3.dist-info/RECORD
