Metadata-Version: 2.1
Name: gp-maps-python
Version: 0.0.3
Summary: Gaussian Processes for orientation preference maps
Home-page: https://github.com/mackelab/gp-maps-python
Author: Dominik Straub
Author-email: straub@psychologie.tu-darmstadt.de
License: UNKNOWN
Platform: UNKNOWN
Classifier: Programming Language :: Python :: 3
Classifier: License :: OSI Approved :: GNU General Public License v3 (GPLv3)
Classifier: Operating System :: OS Independent
Requires-Python: >=3.6
Requires-Dist: scipy (>=1.4.1)
Requires-Dist: numpy (>=1.18.1)
Requires-Dist: matplotlib (>=3.1.3)
Requires-Dist: pingouin (>=0.3.3)
Requires-Dist: scikit-image (>=0.16.2)
Requires-Dist: dill (>=0.3.1.1)
Requires-Dist: PyQt5 (>=5.14.1)
Requires-Dist: scikit-learn (>=0.22.2)
